pyspread/__init__.py
pyspread/__main__.py
pyspread/actions.py
pyspread/cli.py
pyspread/commands.py
pyspread/dialogs.py
pyspread/entryline.py
pyspread/grid.py
pyspread/grid_renderer.py
pyspread/icons.py
pyspread/installer.py
pyspread/main_window.py
pyspread/menus.py
pyspread/panels.py
pyspread/pyspread.py
pyspread/settings.py
pyspread/themes.py
pyspread/toolbar.py
pyspread/widgets.py
pyspread/workflows.py
pyspread/interfaces/__init__.py
pyspread/interfaces/pys.py
pyspread/interfaces/xlsx.py
pyspread/interfaces/test/__init__.py
pyspread/lib/__init__.py
pyspread/lib/attrdict.py
pyspread/lib/charts.py
pyspread/lib/csv.py
pyspread/lib/dataclasses.py
pyspread/lib/exception_handling.py
pyspread/lib/file_helpers.py
pyspread/lib/hashing.py
pyspread/lib/parsers.py
pyspread/lib/qimage2ndarray.py
pyspread/lib/qimage_svg.py
pyspread/lib/selection.py
pyspread/lib/spelltextedit.py
pyspread/lib/string_helpers.py
pyspread/lib/typechecks.py
pyspread/lib/xls_column.py
pyspread/lib/packaging/__init__.py
pyspread/lib/packaging/_structures.py
pyspread/lib/packaging/_typing.py
pyspread/lib/packaging/version.py
pyspread/lib/test/__init__.py
pyspread/lib/test/compat.py
pyspread/lib/test/test_array2qimage.py
pyspread/lib/test/test_csv.py
pyspread/lib/test/test_file_helpers.py
pyspread/lib/test/test_hashing.py
pyspread/lib/test/test_qimageview.py
pyspread/lib/test/test_selection.py
pyspread/lib/test/test_string_helpers.py
pyspread/lib/test/test_xls_column.py
pyspread/model/__init__.py
pyspread/model/model.py
pyspread/model/test/__init__.py
pyspread/model/test/test_model.py
pyspread/share/LICENSE
pyspread/share/applications/io.gitlab.pyspread.pyspread.desktop
pyspread/share/doc/manual/advanced_topics.md
pyspread/share/doc/manual/basic_concepts.md
pyspread/share/doc/manual/edit_menu.md
pyspread/share/doc/manual/file_menu.md
pyspread/share/doc/manual/format_menu.md
pyspread/share/doc/manual/macro_menu.md
pyspread/share/doc/manual/overview.md
pyspread/share/doc/manual/view_menu.md
pyspread-2.4.1.dist-info/licenses/AUTHORS
pyspread-2.4.1.dist-info/licenses/LICENSE
pyspread-2.4.1.dist-info/METADATA
pyspread-2.4.1.dist-info/WHEEL
pyspread-2.4.1.dist-info/entry_points.txt
pyspread-2.4.1.dist-info/top_level.txt
pyspread-2.4.1.dist-info/RECORD
