Metadata-Version: 2.4
Name: pyspread
Version: 2.4.1
Summary: Pyspread is a non-traditional spreadsheet application that is based on and written in the programming language Python.
Home-page: https://pyspread.gitlab.io
Author: Martin Manns
Author-email: mmanns@gmx.net
License: GPL v3 :: GNU General Public License
Project-URL: Bug Tracker, https://gitlab.com/pyspread/pyspread/issues
Project-URL: Documentation, https://pyspread.gitlab.io/docs.html
Project-URL: Source Code, https://gitlab.com/pyspread/pyspread
Keywords: spreadsheet,pyspread
Classifier: Development Status :: 5 - Production/Stable
Classifier: Environment :: X11 Applications :: Qt
Classifier: Environment :: Win32 (MS Windows)
Classifier: Intended Audience :: End Users/Desktop
Classifier: License :: OSI Approved :: GNU General Public License v3 or later (GPLv3+)
Classifier: Natural Language :: English
Classifier: Operating System :: OS Independent
Classifier: Operating System :: POSIX
Classifier: Operating System :: Microsoft
Classifier: Programming Language :: Python :: 3.6
Classifier: Programming Language :: Python :: 3.7
Classifier: Programming Language :: Python :: 3.8
Classifier: Programming Language :: Python :: 3.9
Classifier: Programming Language :: Python :: 3.10
Classifier: Topic :: Office/Business :: Financial :: Spreadsheet
Classifier: Topic :: Scientific/Engineering
Requires-Python: >=3.6
License-File: LICENSE
License-File: AUTHORS
Requires-Dist: numpy>=1.1
Requires-Dist: PyQt6>=6.4
Requires-Dist: setuptools>=40.0
Requires-Dist: markdown2>=2.3
Provides-Extra: matplotlib
Requires-Dist: matplotlib>=1.1.1; extra == "matplotlib"
Provides-Extra: pyenchant
Requires-Dist: pyenchant>=1.1; extra == "pyenchant"
Provides-Extra: pip
Requires-Dist: pip>=18; extra == "pip"
Provides-Extra: python-dateutil
Requires-Dist: python-dateutil>=2.7.0; extra == "python-dateutil"
Provides-Extra: py-moneyed
Requires-Dist: py-moneyed>=2.0; extra == "py-moneyed"
Provides-Extra: rpy2
Requires-Dist: rpy2>=3.4; extra == "rpy2"
Provides-Extra: plotnine
Requires-Dist: plotnine>=0.8; extra == "plotnine"
Provides-Extra: pycel
Requires-Dist: pycel>=1.0b30; extra == "pycel"
Provides-Extra: openpyxl
Requires-Dist: openpyxl>=3.0.7; extra == "openpyxl"
Dynamic: author
Dynamic: author-email
Dynamic: classifier
Dynamic: description
Dynamic: description-content-type
Dynamic: home-page
Dynamic: keywords
Dynamic: license
Dynamic: license-file
Dynamic: project-url
Dynamic: provides-extra
Dynamic: requires-dist
Dynamic: requires-python
Dynamic: summary
